<?xml version="1.0" ?>
<network>
	<nodes>
		<node id="0"/>
		<node id="1"/>
		<node id="2"/>
		<node id="3"/>
		<node id="4"/>
		<node id="5"/>
		<node id="6"/>
		<node id="7"/>
		<node id="8"/>
		<node id="9"/>
		<node id="10"/>
		<node id="11"/>
		<node id="12"/>
		<node id="13"/>
		<node id="14"/>
		<node id="15"/>
		<node id="16"/>
		<node id="17"/>
		<node id="18"/>
		<node id="19"/>
		<node id="20"/>
		<node id="21"/>
		<node id="22"/>
		<node id="23"/>
		<node id="24"/>
		<node id="25"/>
		<node id="26"/>
		<node id="27"/>
		<node id="28"/>
		<node id="29"/>
		<node id="30"/>
		<node id="31"/>
	</nodes>
	<edges>
		<edge directed="false" from="0" to="13"/>
		<edge directed="false" from="0" to="5"/>
		<edge directed="false" from="0" to="14"/>
		<edge directed="false" from="0" to="7"/>
		<edge directed="false" from="0" to="17"/>
		<edge directed="false" from="1" to="9"/>
		<edge directed="false" from="1" to="23"/>
		<edge directed="false" from="1" to="5"/>
		<edge directed="false" from="1" to="17"/>
		<edge directed="false" from="1" to="22"/>
		<edge directed="false" from="2" to="16"/>
		<edge directed="false" from="2" to="8"/>
		<edge directed="false" from="2" to="26"/>
		<edge directed="false" from="2" to="24"/>
		<edge directed="false" from="2" to="30"/>
		<edge directed="false" from="3" to="19"/>
		<edge directed="false" from="3" to="5"/>
		<edge directed="false" from="3" to="9"/>
		<edge directed="false" from="3" to="7"/>
		<edge directed="false" from="3" to="15"/>
		<edge directed="false" from="4" to="19"/>
		<edge directed="false" from="4" to="10"/>
		<edge directed="false" from="4" to="27"/>
		<edge directed="false" from="4" to="25"/>
		<edge directed="false" from="4" to="15"/>
		<edge directed="false" from="5" to="18"/>
		<edge directed="false" from="5" to="21"/>
		<edge directed="false" from="6" to="23"/>
		<edge directed="false" from="6" to="10"/>
		<edge directed="false" from="6" to="31"/>
		<edge directed="false" from="6" to="25"/>
		<edge directed="false" from="6" to="22"/>
		<edge directed="false" from="7" to="16"/>
		<edge directed="false" from="7" to="30"/>
		<edge directed="false" from="7" to="11"/>
		<edge directed="false" from="8" to="20"/>
		<edge directed="false" from="8" to="27"/>
		<edge directed="false" from="8" to="25"/>
		<edge directed="false" from="8" to="31"/>
		<edge directed="false" from="9" to="16"/>
		<edge directed="false" from="9" to="26"/>
		<edge directed="false" from="9" to="12"/>
		<edge directed="false" from="10" to="28"/>
		<edge directed="false" from="10" to="18"/>
		<edge directed="false" from="10" to="21"/>
		<edge directed="false" from="11" to="20"/>
		<edge directed="false" from="11" to="19"/>
		<edge directed="false" from="11" to="27"/>
		<edge directed="false" from="11" to="14"/>
		<edge directed="false" from="12" to="20"/>
		<edge directed="false" from="12" to="23"/>
		<edge directed="false" from="12" to="25"/>
		<edge directed="false" from="12" to="19"/>
		<edge directed="false" from="13" to="28"/>
		<edge directed="false" from="13" to="18"/>
		<edge directed="false" from="13" to="30"/>
		<edge directed="false" from="13" to="24"/>
		<edge directed="false" from="14" to="28"/>
		<edge directed="false" from="14" to="29"/>
		<edge directed="false" from="14" to="21"/>
		<edge directed="false" from="15" to="30"/>
		<edge directed="false" from="15" to="18"/>
		<edge directed="false" from="15" to="26"/>
		<edge directed="false" from="16" to="20"/>
		<edge directed="false" from="16" to="17"/>
		<edge directed="false" from="17" to="29"/>
		<edge directed="false" from="17" to="24"/>
		<edge directed="false" from="18" to="22"/>
		<edge directed="false" from="19" to="21"/>
		<edge directed="false" from="20" to="29"/>
		<edge directed="false" from="21" to="23"/>
		<edge directed="false" from="22" to="24"/>
		<edge directed="false" from="22" to="26"/>
		<edge directed="false" from="23" to="29"/>
		<edge directed="false" from="24" to="31"/>
		<edge directed="false" from="25" to="26"/>
		<edge directed="false" from="27" to="28"/>
		<edge directed="false" from="27" to="30"/>
		<edge directed="false" from="28" to="31"/>
		<edge directed="false" from="29" to="31"/>
	</edges>
</network>
